Connor-0.6.1.dist-info/METADATA
Connor-0.6.1.dist-info/RECORD
Connor-0.6.1.dist-info/WHEEL
Connor-0.6.1.dist-info/entry_points.txt
Connor-0.6.1.dist-info/top_level.txt
connor/__init__.py
connor/__main__.py
connor/command_parser.py
connor/command_validator.py
connor/connor.py
connor/family.py
connor/family_handler.py
connor/utils.py
connor/consam/__init__.py
connor/consam/alignments.py
connor/consam/bamflag.py
connor/consam/bamtag.py
connor/consam/pysamwrapper.py
connor/consam/readers.py
connor/consam/writers.py
