Metadata-Version: 2.1
Name: Connor
Version: 0.6.1
Summary: Command-line tool to deduplicate reads in bam files based on custom inline barcoding.
Home-page: https://github.com/umich-brcf-bioinf/Connor
Author: University of Michigan Bioinformatics Core
Author-email: bfx-connor@umich.edu
License: Apache
Keywords: bioinformatic exome-seq DNA-seq BAM
Platform: UNKNOWN
Classifier: Development Status :: 5 - Production/Stable
Classifier: Environment :: Console
Classifier: Intended Audience :: Science/Research
Classifier: License :: OSI Approved :: Apache Software License
Classifier: Operating System :: Unix
Classifier: Operating System :: MacOS
Classifier: Programming Language :: Python :: 2.7
Classifier: Programming Language :: Python :: 3
Classifier: Topic :: Scientific/Engineering :: Bio-Informatics
Requires-Dist: pysam (>=0.8.4)
Requires-Dist: sortedcontainers (>=1.5.3)
